undetected_edgedriver/__init__.py
undetected_edgedriver/cdp.py
undetected_edgedriver/dprocess.py
undetected_edgedriver/options.py
undetected_edgedriver/patcher.py
undetected_edgedriver/reactor.py
undetected_edgedriver/webelement.py
undetected_edgedriver-3.1.6.4.dist-info/LICENSE
undetected_edgedriver-3.1.6.4.dist-info/METADATA
undetected_edgedriver-3.1.6.4.dist-info/WHEEL
undetected_edgedriver-3.1.6.4.dist-info/top_level.txt
undetected_edgedriver-3.1.6.4.dist-info/RECORD
